chartmogul/__init__.py
chartmogul/errors.py
chartmogul/resource.py
chartmogul/retry_request.py
chartmogul/version.py
chartmogul/api/__init__.py
chartmogul/api/account.py
chartmogul/api/activities_export.py
chartmogul/api/activity.py
chartmogul/api/attributes.py
chartmogul/api/config.py
chartmogul/api/contact.py
chartmogul/api/custom_attrs.py
chartmogul/api/customer.py
chartmogul/api/data_source.py
chartmogul/api/invoice.py
chartmogul/api/metrics.py
chartmogul/api/ping.py
chartmogul/api/plan.py
chartmogul/api/plan_group.py
chartmogul/api/plan_group_plans.py
chartmogul/api/subscription_event.py
chartmogul/api/tags.py
chartmogul/api/transaction.py
chartmogul/api/customers/__init__.py
chartmogul/api/customers/activity.py
chartmogul/api/customers/subscription.py
chartmogul-4.0.0.dist-info/LICENSE.txt
chartmogul-4.0.0.dist-info/METADATA
chartmogul-4.0.0.dist-info/WHEEL
chartmogul-4.0.0.dist-info/top_level.txt
chartmogul-4.0.0.dist-info/RECORD
