Metadata-Version: 2.1
Name: chartmogul
Version: 4.0.0
Summary: Python library for ChartMogul API.
Home-page: https://chartmogul.com
Download-URL: https://github.com/chartmogul/chartmogul-python/tarball/v4.0.0
Author: Petr Kopac (ChartMogul Ltd.)
Author-email: petr@chartmogul.com
License: MIT
Classifier: Programming Language :: Python
Classifier: Programming Language :: Python :: 3
Classifier: Programming Language :: Python :: 3.8
Classifier: Programming Language :: Python :: 3.9
Classifier: Programming Language :: Python :: 3.10
Classifier: Programming Language :: Python :: 3.11
Classifier: Programming Language :: Python :: 3.12
License-File: LICENSE.txt
Requires-Dist: requests >=2.31.0
Requires-Dist: uritemplate >=4.1.1
Requires-Dist: promise >=2.3.0
Requires-Dist: marshmallow >=3.19.0
Requires-Dist: future >=0.18.3
Requires-Dist: urllib3 <=2.0.4
